moteinopy
