Metadata-Version: 1.1
Name: moteinopy
Version: 1.1.1b0
Summary: Moteino communication module
Home-page: https://github.com/Steinarr134/moteinopy
Author: SteinarrHrafn
Author-email: steinarrrrrrrrrr+moteinopy@gmail.com
License: MIT
Keywords: moteino communication rfm69
Platform: UNKNOWN
Classifier: Development Status :: 4 - Beta
Classifier: Intended Audience :: Developers
Classifier: Topic :: Software Development :: Libraries :: Python Modules
Classifier: License :: OSI Approved :: MIT License
Classifier: Programming Language :: Python :: 2.7
Classifier: Programming Language :: Python :: 3.5
